compress_and_upload_to_do_spaces/__init__.py
compress_and_upload_to_do_spaces/upload_service.py
compress_and_upload_to_do_spaces-0.1.4.dist-info/METADATA
compress_and_upload_to_do_spaces-0.1.4.dist-info/WHEEL
compress_and_upload_to_do_spaces-0.1.4.dist-info/top_level.txt
compress_and_upload_to_do_spaces-0.1.4.dist-info/RECORD
