Metadata-Version: 2.4
Name: compress_and_upload_to_do_spaces
Version: 0.1.4
Summary: Python service for compressing and uploading images to DigitalOcean Spaces
Author-email: Johannes <you@example.com>
License-Expression: MIT
Requires-Dist: boto3
Requires-Dist: tinify
Requires-Dist: requests
